{
  "annotations": [
    {
      "label": "salmon",
      "bbox": [
        0,
        0,
        480,
        480
      ],
      "color": [
        100,
        150,
        200
      ]
    },
    {
      "label": "pumpkin",
      "bbox": [
        0,
        480,
        480,
        960
      ],
      "color": [
        50,
        100,
        150
      ]
    },
    {
      "label": "mushroom and baby corn dish",
      "bbox": [
        480,
        0,
        960,
        480
      ],
      "color": [
        150,
        200,
        100
      ]
    }
  ]
}